gais_json_convertor
