Metadata-Version: 1.0
Name: gais-json-convertor
Version: 0.0.2
Summary: Convertor for GAIS format and JSON format.
Home-page: https://github.com/wshs0713/gais_json_convertor.git
Author: Szu-Hsuan, Wu
Author-email: shuan0713@gmail.com
License: docs/LICENSE.txt
Keywords: GAIS,JSON,gais_json_convertor
Platform: UNKNOWN
